elevenlab/__init__.py
elevenlab/pdisk.py
elevenlab/type.py
elevenlab-0.0.1.dist-info/LICENSE
elevenlab-0.0.1.dist-info/METADATA
elevenlab-0.0.1.dist-info/WHEEL
elevenlab-0.0.1.dist-info/top_level.txt
elevenlab-0.0.1.dist-info/RECORD
