Metadata-Version: 2.1
Name: elevenlab
Version: 0.0.1
Summary: An Unofficial Asynchronous Python version of elevenlabs API wrapper
Author-email: kalanakt <kalanakt@uvew.xyz>
Project-URL: Homepage, https://github.com/kalanakt/elevenlab
Project-URL: Bug Tracker, https://github.com/kalanakt/elevenlab/issues
Classifier: Programming Language :: Python :: 3
Classifier: License :: OSI Approved :: MIT License
Classifier: Operating System :: OS Independent
Requires-Python: >=3.7
License-File: LICENSE
